Metadata-Version: 2.1
Name: objx
Version: 124
Summary: objects
Author-email: Bart Thate <rssbotd@gmail.com>
License: Public Domain
Project-URL: home, https://pypi.org/project/objx
Project-URL: bugs, https://github.com/rssbotd/objx/issues
Project-URL: source, https://github.com/rssbotd/objx
Classifier: Development Status :: 3 - Alpha
Classifier: License :: Public Domain
Classifier: Operating System :: Unix
Classifier: Programming Language :: Python
Classifier: Topic :: Utilities
